mayaku/__init__.py
mayaku-0.1.0.dist-info/licenses/LICENSE
mayaku-0.1.0.dist-info/METADATA
mayaku-0.1.0.dist-info/WHEEL
mayaku-0.1.0.dist-info/top_level.txt
mayaku-0.1.0.dist-info/RECORD
